pyserum/__init__.py
pyserum/async_connection.py
pyserum/async_open_orders_account.py
pyserum/async_utils.py
pyserum/connection.py
pyserum/enums.py
pyserum/instructions.py
pyserum/open_orders_account.py
pyserum/py.typed
pyserum/utils.py
pyserum/_layouts/__init__.py
pyserum/_layouts/account_flags.py
pyserum/_layouts/instructions.py
pyserum/_layouts/market.py
pyserum/_layouts/open_orders.py
pyserum/_layouts/queue.py
pyserum/_layouts/slab.py
pyserum/market/__init__.py
pyserum/market/async_market.py
pyserum/market/core.py
pyserum/market/market.py
pyserum/market/orderbook.py
pyserum/market/state.py
pyserum/market/types.py
pyserum/market/_internal/__init__.py
pyserum/market/_internal/queue.py
pyserum/market/_internal/slab.py
pyopenbook-0.7.3a0.dist-info/LICENSE
pyopenbook-0.7.3a0.dist-info/METADATA
pyopenbook-0.7.3a0.dist-info/WHEEL
pyopenbook-0.7.3a0.dist-info/top_level.txt
pyopenbook-0.7.3a0.dist-info/RECORD
